Metadata-Version: 2.1
Name: pyuio
Version: 0.1.0
Summary: A package to expose the Linux Userspace IO to python
Home-page: https://github.com/GOcontroll/pyuio
Author: Maud Spierings
Author-email: maud_spierings@hotmail.com
License: GLP V2.0
Platform: UNKNOWN
Classifier: Development Status :: 5 - Production/Stable
Classifier: Intended Audience :: Developers
Classifier: License :: OSI Approved :: GNU General Public License v2 (GPLv2)
Classifier: Operating System :: POSIX :: Linux
Classifier: Programming Language :: Python :: 3
